kms_client/__init__.py
kms_client/logger.py
kms_client/retrieve_keys.py
kms_client/config/__init__.py
kms_client/config/loader.py
kms_client-0.0.2.dist-info/LICENSE
kms_client-0.0.2.dist-info/METADATA
kms_client-0.0.2.dist-info/WHEEL
kms_client-0.0.2.dist-info/top_level.txt
kms_client-0.0.2.dist-info/RECORD
